{"name":"Verify report versioning with admin role","id":"module-events-tests;verify-report-versioning-with-admin-role","testSteps":[{"number":1,"description":"Given I want to login admin to web page GAO","duration":12658,"startTime":"2021-02-11T21:45:49.751338600-05:00[America/Bogota]","screenshots":[{"screenshot":"b8a66a572ef1c416d8b78a019fd2a907e49164fc090c849a9ffc5dd6523b6d4d.png","timeStamp":1613097950105}],"precondition":false,"level":0,"lineNumber":0,"children":[{"number":2,"description":"Xm open browser","duration":9797,"startTime":"2021-02-11T21:45:50.192238300-05:00[America/Bogota]","screenshots":[{"screenshot":"b8a66a572ef1c416d8b78a019fd2a907e49164fc090c849a9ffc5dd6523b6d4d.png","timeStamp":1613097950465},{"screenshot":"e445104747dc680e3d2a1a434d54eb155f6b0bfb6906e3184c3c7b80ea02edfc.png","timeStamp":1613097959990}],"result":"SUCCESS","precondition":false,"level":1,"lineNumber":0,"children":[{"number":3,"description":"Xm opens the http://automationpractice.com/index.php","duration":9491,"startTime":"2021-02-11T21:45:50.488271-05:00[America/Bogota]","screenshots":[{"screenshot":"b8a66a572ef1c416d8b78a019fd2a907e49164fc090c849a9ffc5dd6523b6d4d.png","timeStamp":1613097950493},{"screenshot":"e445104747dc680e3d2a1a434d54eb155f6b0bfb6906e3184c3c7b80ea02edfc.png","timeStamp":1613097959979}],"result":"SUCCESS","precondition":false,"level":2,"lineNumber":0}]},{"number":4,"description":"Xm login","duration":2398,"startTime":"2021-02-11T21:46:00.010079700-05:00[America/Bogota]","screenshots":[{"screenshot":"e445104747dc680e3d2a1a434d54eb155f6b0bfb6906e3184c3c7b80ea02edfc.png","timeStamp":1613097960013}],"exception":{"errorType":"org.openqa.selenium.NoSuchWindowException","message":"no such window: target window already closed\nfrom unknown error: web view not found\n  (Session info: chrome\u003d88.0.4324.150)\nBuild info: version: \u00273.141.59\u0027, revision: \u0027e82be7d358\u0027, time: \u00272018-11-14T08:17:03\u0027\nSystem info: host: \u0027DESKTOP-CPRMIED\u0027, ip: \u0027192.168.12.166\u0027, os.name: \u0027Windows 10\u0027, os.arch: \u0027amd64\u0027, os.version: \u002710.0\u0027, java.version: \u002715.0.1\u0027\nDriver info: org.openqa.selenium.chrome.ChromeDriver\nCapabilities {acceptInsecureCerts: false, browserName: chrome, browserVersion: 88.0.4324.150, chrome: {chromedriverVersion: 88.0.4324.96 (68dba2d8a0b14..., userDataDir: C:\\Users\\jmorales\\AppData\\L...}, goog:chromeOptions: {debuggerAddress: localhost:55743}, javascriptEnabled: true, networkConnectionEnabled: false, pageLoadStrategy: normal, platform: WINDOWS, platformName: WINDOWS, proxy: Proxy(), setWindowRect: true, strictFileInteractability: false, timeouts: {implicit: 0, pageLoad: 300000, script: 30000}, unhandledPromptBehavior: dismiss and notify, webauthn:extension:largeBlob: true, webauthn:virtualAuthenticators: true}\nSession ID: d8835803d5537bfeee30e2bc7c35c6bf\n*** Element info: {Using\u003did, value\u003dNombreUsuario}","stackTrace":[{"classLoaderName":"app","declaringClass":"com.co.gao.tasks.Login","methodName":"performAs","fileName":"Login.java","lineNumber":34,"format":1},{"classLoaderName":"app","declaringClass":"com.co.gao.stepdefinitions.postoperativo.CommonSteps","methodName":"iWantToLoginAdminToWebPageGAO","fileName":"CommonSteps.java","lineNumber":62,"format":1},{"classLoaderName":"app","declaringClass":"cucumber.runner.PickleStepDefinitionMatch","methodName":"runStep","fileName":"PickleStepDefinitionMatch.java","lineNumber":50,"format":1},{"classLoaderName":"app","declaringClass":"cucumber.runner.TestStep","methodName":"executeStep","fileName":"TestStep.java","lineNumber":63,"format":1},{"classLoaderName":"app","declaringClass":"cucumber.runner.TestStep","methodName":"run","fileName":"TestStep.java","lineNumber":49,"format":1},{"classLoaderName":"app","declaringClass":"cucumber.runner.PickleStepTestStep","methodName":"run","fileName":"PickleStepTestStep.java","lineNumber":43,"format":1},{"classLoaderName":"app","declaringClass":"cucumber.runner.TestCase","methodName":"run","fileName":"TestCase.java","lineNumber":44,"format":1},{"classLoaderName":"app","declaringClass":"cucumber.runner.Runner","methodName":"runPickle","fileName":"Runner.java","lineNumber":40,"format":1},{"classLoaderName":"app","declaringClass":"org.eclipse.jdt.internal.junit4.runner.JUnit4TestReference","methodName":"run","fileName":"JUnit4TestReference.java","lineNumber":89,"format":1},{"classLoaderName":"app","declaringClass":"org.eclipse.jdt.internal.junit.runner.TestExecution","methodName":"run","fileName":"TestExecution.java","lineNumber":41,"format":1},{"classLoaderName":"app","declaringClass":"org.eclipse.jdt.internal.junit.runner.RemoteTestRunner","methodName":"runTests","fileName":"RemoteTestRunner.java","lineNumber":542,"format":1},{"classLoaderName":"app","declaringClass":"org.eclipse.jdt.internal.junit.runner.RemoteTestRunner","methodName":"runTests","fileName":"RemoteTestRunner.java","lineNumber":770,"format":1},{"classLoaderName":"app","declaringClass":"org.eclipse.jdt.internal.junit.runner.RemoteTestRunner","methodName":"run","fileName":"RemoteTestRunner.java","lineNumber":464,"format":1},{"classLoaderName":"app","declaringClass":"org.eclipse.jdt.internal.junit.runner.RemoteTestRunner","methodName":"main","fileName":"RemoteTestRunner.java","lineNumber":210,"format":1}]},"result":"ERROR","precondition":false,"level":1,"lineNumber":0,"children":[{"number":5,"description":"Xm enters \u0027GAO50100\u0027 into Name user","duration":2312,"startTime":"2021-02-11T21:46:00.082038-05:00[America/Bogota]","screenshots":[{"screenshot":"e445104747dc680e3d2a1a434d54eb155f6b0bfb6906e3184c3c7b80ea02edfc.png","timeStamp":1613097960696}],"exception":{"errorType":"org.openqa.selenium.NoSuchWindowException","message":"no such window: target window already closed\nfrom unknown error: web view not found\n  (Session info: chrome\u003d88.0.4324.150)\nBuild info: version: \u00273.141.59\u0027, revision: \u0027e82be7d358\u0027, time: \u00272018-11-14T08:17:03\u0027\nSystem info: host: \u0027DESKTOP-CPRMIED\u0027, ip: \u0027192.168.12.166\u0027, os.name: \u0027Windows 10\u0027, os.arch: \u0027amd64\u0027, os.version: \u002710.0\u0027, java.version: \u002715.0.1\u0027\nDriver info: org.openqa.selenium.chrome.ChromeDriver\nCapabilities {acceptInsecureCerts: false, browserName: chrome, browserVersion: 88.0.4324.150, chrome: {chromedriverVersion: 88.0.4324.96 (68dba2d8a0b14..., userDataDir: C:\\Users\\jmorales\\AppData\\L...}, goog:chromeOptions: {debuggerAddress: localhost:55743}, javascriptEnabled: true, networkConnectionEnabled: false, pageLoadStrategy: normal, platform: WINDOWS, platformName: WINDOWS, proxy: Proxy(), setWindowRect: true, strictFileInteractability: false, timeouts: {implicit: 0, pageLoad: 300000, script: 30000}, unhandledPromptBehavior: dismiss and notify, webauthn:extension:largeBlob: true, webauthn:virtualAuthenticators: true}\nSession ID: d8835803d5537bfeee30e2bc7c35c6bf\n*** Element info: {Using\u003did, value\u003dNombreUsuario}","stackTrace":[{"classLoaderName":"app","declaringClass":"com.co.gao.tasks.Login","methodName":"performAs","fileName":"Login.java","lineNumber":34,"format":1},{"classLoaderName":"app","declaringClass":"com.co.gao.stepdefinitions.postoperativo.CommonSteps","methodName":"iWantToLoginAdminToWebPageGAO","fileName":"CommonSteps.java","lineNumber":62,"format":1},{"classLoaderName":"app","declaringClass":"cucumber.runner.PickleStepDefinitionMatch","methodName":"runStep","fileName":"PickleStepDefinitionMatch.java","lineNumber":50,"format":1},{"classLoaderName":"app","declaringClass":"cucumber.runner.TestStep","methodName":"executeStep","fileName":"TestStep.java","lineNumber":63,"format":1},{"classLoaderName":"app","declaringClass":"cucumber.runner.TestStep","methodName":"run","fileName":"TestStep.java","lineNumber":49,"format":1},{"classLoaderName":"app","declaringClass":"cucumber.runner.PickleStepTestStep","methodName":"run","fileName":"PickleStepTestStep.java","lineNumber":43,"format":1},{"classLoaderName":"app","declaringClass":"cucumber.runner.TestCase","methodName":"run","fileName":"TestCase.java","lineNumber":44,"format":1},{"classLoaderName":"app","declaringClass":"cucumber.runner.Runner","methodName":"runPickle","fileName":"Runner.java","lineNumber":40,"format":1},{"classLoaderName":"app","declaringClass":"org.eclipse.jdt.internal.junit4.runner.JUnit4TestReference","methodName":"run","fileName":"JUnit4TestReference.java","lineNumber":89,"format":1},{"classLoaderName":"app","declaringClass":"org.eclipse.jdt.internal.junit.runner.TestExecution","methodName":"run","fileName":"TestExecution.java","lineNumber":41,"format":1},{"classLoaderName":"app","declaringClass":"org.eclipse.jdt.internal.junit.runner.RemoteTestRunner","methodName":"runTests","fileName":"RemoteTestRunner.java","lineNumber":542,"format":1},{"classLoaderName":"app","declaringClass":"org.eclipse.jdt.internal.junit.runner.RemoteTestRunner","methodName":"runTests","fileName":"RemoteTestRunner.java","lineNumber":770,"format":1},{"classLoaderName":"app","declaringClass":"org.eclipse.jdt.internal.junit.runner.RemoteTestRunner","methodName":"run","fileName":"RemoteTestRunner.java","lineNumber":464,"format":1},{"classLoaderName":"app","declaringClass":"org.eclipse.jdt.internal.junit.runner.RemoteTestRunner","methodName":"main","fileName":"RemoteTestRunner.java","lineNumber":210,"format":1}]},"result":"ERROR","precondition":false,"level":2,"lineNumber":0}]}]},{"number":6,"description":"When I upload several files","duration":52,"startTime":"2021-02-11T21:46:02.423165600-05:00[America/Bogota]","precondition":false,"level":0,"lineNumber":0,"children":[{"number":7,"description":"Xm select menu","duration":1,"startTime":"2021-02-11T21:46:02.441154700-05:00[America/Bogota]","result":"SKIPPED","precondition":false,"level":1,"lineNumber":0},{"number":8,"description":"Xm report versioning task","duration":1,"startTime":"2021-02-11T21:46:02.469138900-05:00[America/Bogota]","result":"SKIPPED","precondition":false,"level":1,"lineNumber":0}]},{"number":9,"description":"Then I verify the versioning","duration":42,"startTime":"2021-02-11T21:46:02.478134100-05:00[America/Bogota]","result":"SUCCESS","precondition":false,"level":0,"lineNumber":0,"children":[{"number":10,"description":"Xm select menu","duration":1,"startTime":"2021-02-11T21:46:02.492125700-05:00[America/Bogota]","result":"SKIPPED","precondition":false,"level":1,"lineNumber":0},{"number":11,"description":"Xm verifity report versioning","duration":0,"startTime":"2021-02-11T21:46:02.508116800-05:00[America/Bogota]","result":"SKIPPED","precondition":false,"level":1,"lineNumber":0}]}],"userStory":{"id":"module-events-tests","storyName":"Module Events Tests","path":"src/test/resources/features/events/CreateAnlysisCase.feature","type":"feature"},"featureTag":{"name":"Events/Module Events Tests","type":"feature","displayName":"Events/Module Events Tests"},"title":"Verify report versioning with admin role","tags":[{"name":"Events","type":"tag","displayName":"Events"},{"name":"ReportVersioning","type":"tag","displayName":"ReportVersioning"}],"startTime":"2021-02-11T21:45:45.386922500-05:00[America/Bogota]","duration":17140,"testFailureCause":{"errorType":"org.openqa.selenium.NoSuchWindowException","message":"no such window: target window already closed\nfrom unknown error: web view not found\n  (Session info: chrome\u003d88.0.4324.150)\nBuild info: version: \u00273.141.59\u0027, revision: \u0027e82be7d358\u0027, time: \u00272018-11-14T08:17:03\u0027\nSystem info: host: \u0027DESKTOP-CPRMIED\u0027, ip: \u0027192.168.12.166\u0027, os.name: \u0027Windows 10\u0027, os.arch: \u0027amd64\u0027, os.version: \u002710.0\u0027, java.version: \u002715.0.1\u0027\nDriver info: org.openqa.selenium.chrome.ChromeDriver\nCapabilities {acceptInsecureCerts: false, browserName: chrome, browserVersion: 88.0.4324.150, chrome: {chromedriverVersion: 88.0.4324.96 (68dba2d8a0b14..., userDataDir: C:\\Users\\jmorales\\AppData\\L...}, goog:chromeOptions: {debuggerAddress: localhost:55743}, javascriptEnabled: true, networkConnectionEnabled: false, pageLoadStrategy: normal, platform: WINDOWS, platformName: WINDOWS, proxy: Proxy(), setWindowRect: true, strictFileInteractability: false, timeouts: {implicit: 0, pageLoad: 300000, script: 30000}, unhandledPromptBehavior: dismiss and notify, webauthn:extension:largeBlob: true, webauthn:virtualAuthenticators: true}\nSession ID: d8835803d5537bfeee30e2bc7c35c6bf\n*** Element info: {Using\u003did, value\u003dNombreUsuario}","stackTrace":[{"classLoaderName":"app","declaringClass":"com.co.gao.tasks.Login","methodName":"performAs","fileName":"Login.java","lineNumber":34,"format":1},{"classLoaderName":"app","declaringClass":"com.co.gao.stepdefinitions.postoperativo.CommonSteps","methodName":"iWantToLoginAdminToWebPageGAO","fileName":"CommonSteps.java","lineNumber":62,"format":1},{"classLoaderName":"app","declaringClass":"cucumber.runner.PickleStepDefinitionMatch","methodName":"runStep","fileName":"PickleStepDefinitionMatch.java","lineNumber":50,"format":1},{"classLoaderName":"app","declaringClass":"cucumber.runner.TestStep","methodName":"executeStep","fileName":"TestStep.java","lineNumber":63,"format":1},{"classLoaderName":"app","declaringClass":"cucumber.runner.TestStep","methodName":"run","fileName":"TestStep.java","lineNumber":49,"format":1},{"classLoaderName":"app","declaringClass":"cucumber.runner.PickleStepTestStep","methodName":"run","fileName":"PickleStepTestStep.java","lineNumber":43,"format":1},{"classLoaderName":"app","declaringClass":"cucumber.runner.TestCase","methodName":"run","fileName":"TestCase.java","lineNumber":44,"format":1},{"classLoaderName":"app","declaringClass":"cucumber.runner.Runner","methodName":"runPickle","fileName":"Runner.java","lineNumber":40,"format":1},{"classLoaderName":"app","declaringClass":"org.eclipse.jdt.internal.junit4.runner.JUnit4TestReference","methodName":"run","fileName":"JUnit4TestReference.java","lineNumber":89,"format":1},{"classLoaderName":"app","declaringClass":"org.eclipse.jdt.internal.junit.runner.TestExecution","methodName":"run","fileName":"TestExecution.java","lineNumber":41,"format":1},{"classLoaderName":"app","declaringClass":"org.eclipse.jdt.internal.junit.runner.RemoteTestRunner","methodName":"runTests","fileName":"RemoteTestRunner.java","lineNumber":542,"format":1},{"classLoaderName":"app","declaringClass":"org.eclipse.jdt.internal.junit.runner.RemoteTestRunner","methodName":"runTests","fileName":"RemoteTestRunner.java","lineNumber":770,"format":1},{"classLoaderName":"app","declaringClass":"org.eclipse.jdt.internal.junit.runner.RemoteTestRunner","methodName":"run","fileName":"RemoteTestRunner.java","lineNumber":464,"format":1},{"classLoaderName":"app","declaringClass":"org.eclipse.jdt.internal.junit.runner.RemoteTestRunner","methodName":"main","fileName":"RemoteTestRunner.java","lineNumber":210,"format":1}]},"testFailureClassname":"org.openqa.selenium.NoSuchWindowException","testFailureMessage":"no such window: target window already closed\nfrom unknown error: web view not found\n  (Session info: chrome\u003d88.0.4324.150)\nBuild info: version: \u00273.141.59\u0027, revision: \u0027e82be7d358\u0027, time: \u00272018-11-14T08:17:03\u0027\nSystem info: host: \u0027DESKTOP-CPRMIED\u0027, ip: \u0027192.168.12.166\u0027, os.name: \u0027Windows 10\u0027, os.arch: \u0027amd64\u0027, os.version: \u002710.0\u0027, java.version: \u002715.0.1\u0027\nDriver info: org.openqa.selenium.chrome.ChromeDriver\nCapabilities {acceptInsecureCerts: false, browserName: chrome, browserVersion: 88.0.4324.150, chrome: {chromedriverVersion: 88.0.4324.96 (68dba2d8a0b14..., userDataDir: C:\\Users\\jmorales\\AppData\\L...}, goog:chromeOptions: {debuggerAddress: localhost:55743}, javascriptEnabled: true, networkConnectionEnabled: false, pageLoadStrategy: normal, platform: WINDOWS, platformName: WINDOWS, proxy: Proxy(), setWindowRect: true, strictFileInteractability: false, timeouts: {implicit: 0, pageLoad: 300000, script: 30000}, unhandledPromptBehavior: dismiss and notify, webauthn:extension:largeBlob: true, webauthn:virtualAuthenticators: true}\nSession ID: d8835803d5537bfeee30e2bc7c35c6bf\n*** Element info: {Using\u003did, value\u003dNombreUsuario}","testFailureSummary":"ERROR;org.openqa.selenium.NoSuchWindowException;no such window: target window already closed\nfrom unknown error: web view not found\n  (Session info: chrome\u003d88.0.4324.150)\nBuild info: version: \u00273.141.59\u0027, revision: \u0027e82be7d358\u0027, time: \u00272018-11-14T08:17:03\u0027\nSystem info: host: \u0027DESKTOP-CPRMIED\u0027, ip: \u0027192.168.12.166\u0027, os.name: \u0027Windows 10\u0027, os.arch: \u0027amd64\u0027, os.version: \u002710.0\u0027, java.version: \u002715.0.1\u0027\nDriver info: org.openqa.selenium.chrome.ChromeDriver\nCapabilities {acceptInsecureCerts: false, browserName: chrome, browserVersion: 88.0.4324.150, chrome: {chromedriverVersion: 88.0.4324.96 (68dba2d8a0b14..., userDataDir: C:\\Users\\jmorales\\AppData\\L...}, goog:chromeOptions: {debuggerAddress: localhost:55743}, javascriptEnabled: true, networkConnectionEnabled: false, pageLoadStrategy: normal, platform: WINDOWS, platformName: WINDOWS, proxy: Proxy(), setWindowRect: true, strictFileInteractability: false, timeouts: {implicit: 0, pageLoad: 300000, script: 30000}, unhandledPromptBehavior: dismiss and notify, webauthn:extension:largeBlob: true, webauthn:virtualAuthenticators: true}\nSession ID: d8835803d5537bfeee30e2bc7c35c6bf\n*** Element info: {Using\u003did, value\u003dNombreUsuario};Login.java","projectKey":"","annotatedResult":"ERROR","sessionId":"d8835803d5537bfeee30e2bc7c35c6bf","driver":"chrome","isManualTestingUpToDate":false,"manual":false,"testSource":"Cucumber","actors":[{"name":"Xm","can":["browse the web"]}],"result":"ERROR"}